googleauthentication/GoogleAuthentication.py
googleauthentication/__init__.py
googleauthentication/core/__init__.py
googleauthentication/core/encrypt.py
googleauthentication-0.0.10.dist-info/LICENSE
googleauthentication-0.0.10.dist-info/METADATA
googleauthentication-0.0.10.dist-info/WHEEL
googleauthentication-0.0.10.dist-info/top_level.txt
googleauthentication-0.0.10.dist-info/RECORD
