Metadata-Version: 2.1
Name: googleauthentication
Version: 0.0.10
Summary: A meta package to be connected to Google services
Home-page: https://github.com/dacker-team/googleauthentication
Author: Dacker
Author-email: hello@dacker.co
License: UNKNOWN
Platform: UNKNOWN
Classifier: Programming Language :: Python :: 3
Classifier: License :: OSI Approved :: MIT License
Classifier: Operating System :: OS Independent
Requires-Python: >=3
Requires-Dist: google-api-python-client (==1.7.11)
Requires-Dist: google-auth (==1.6.3)
Requires-Dist: google-auth-httplib2 (==0.0.3)
Requires-Dist: google-auth-oauthlib (==0.4.0)
Requires-Dist: cryptography (>=2.7)
Requires-Dist: dbstream (>=0.0.12)
